hello_mars/__init__.py
hello_mars/greetings.py
tests/__init__.py
tests/test_hello_mars.py
hello_mars_pattern-0.1.0.dist-info/LICENSE
hello_mars_pattern-0.1.0.dist-info/METADATA
hello_mars_pattern-0.1.0.dist-info/WHEEL
hello_mars_pattern-0.1.0.dist-info/top_level.txt
hello_mars_pattern-0.1.0.dist-info/RECORD
